god_mode/__init__.py
god_mode/crypt.py
god_mode/crypt2.py
god_mode/metadata_rw.py
god_mode-1.1.3.dist-info/METADATA
god_mode-1.1.3.dist-info/WHEEL
god_mode-1.1.3.dist-info/entry_points.txt
god_mode-1.1.3.dist-info/top_level.txt
god_mode-1.1.3.dist-info/RECORD
