Metadata-Version: 2.1
Name: god-mode
Version: 1.1.3
Summary: Python 3 script to easy encrypt/decrypt files.
Home-page: UNKNOWN
Author: Nicolas Lettiere
Author-email: braum.exe@gmail.com
License: UNKNOWN
Platform: any
Classifier: Programming Language :: Python :: 3
Classifier: License :: OSI Approved :: MIT License
Classifier: Operating System :: OS Independent
Requires-Dist: pyAesCrypt (==0.4.2)
Requires-Dist: colorama (==0.4.1)
Requires-Dist: PyYAML (==3.13)
Requires-Dist: binaryornot (==0.4.4)
